{"v":"5.6.8","fr":29.9700012207031,"ip":0,"op":455.00001853253,"w":1920,"h":1426,"nm":"Header BG 2","ddd":0,"assets":[{"id":"comp_0","layers":[{"ddd":0,"ind":1,"ty":4,"nm":"01","sr":1,"ks":{"o":{"a":0,"k":100,"ix":11},"r":{"a":0,"k":0,"ix":10},"p":{"a":0,"k":[799.117,613.618,0],"ix":2},"a":{"a":0,"k":[218.217,218.164,0],"ix":1},"s":{"a":0,"k":[100,100,100],"ix":6}},"ao":0,"shapes":[{"ty":"gr","it":[{"ind":0,"ty":"sh","ix":1,"ks":{"a":0,"k":{"i":[[0,0],[0.491,19.106],[-3.193,14.032],[-18.743,18.002],[-34.907,-1.634],[-8.594,1.041],[0.122,43.168],[54.925,-12.35],[-0.736,-40.639],[0.09,-7.549],[21.143,-23.108],[34.552,-0.642],[15.925,-4.878],[-53.541,-44.809],[-28.203,42.376]],"o":[[11.025,-15.765],[-0.254,-14.22],[5.28,-25.439],[25.707,-24.824],[8.534,0.166],[42.93,-4.606],[0.901,-56.302],[-39.94,8.25],[-0.109,7.56],[-0.371,31.02],[-23.548,25.738],[-16.438,0.106],[-66.815,19.611],[38.526,33.068],[0,0]],"v":[[-35.833,167.334],[-20.44,113.402],[-18.162,70.954],[19.159,3.887],[114.213,-32.368],[140.126,-32.957],[217.066,-118.723],[110.148,-205.564],[41.669,-118.956],[41.901,-96.324],[7.849,-12.121],[-83.695,30.099],[-133.047,33.454],[-164.426,184.846],[-35.944,167.497]],"c":true},"ix":2},"nm":"Path 1","mn":"ADBE Vector Shape - Group","hd":false},{"ty":"fl","c":{"a":0,"k":[0.145097994337,0.713725968903,0.521568986481,1],"ix":4},"o":{"a":1,"k":[{"i":{"x":[0.667],"y":[1]},"o":{"x":[0.167],"y":[0]},"t":74,"s":[0]},{"i":{"x":[0.667],"y":[1]},"o":{"x":[0.167],"y":[0]},"t":189,"s":[3]},{"t":323.00001315606,"s":[0]}],"ix":5,"x":"var $bm_rt;\n$bm_rt = loopOut();"},"r":1,"bm":0,"nm":"Fill 1","mn":"ADBE Vector Graphic - Fill","hd":false},{"ty":"tr","p":{"a":0,"k":[218.217,218.164],"ix":2},"a":{"a":0,"k":[0,0],"ix":1},"s":{"a":0,"k":[100,100],"ix":3},"r":{"a":0,"k":0,"ix":6},"o":{"a":0,"k":100,"ix":7},"sk":{"a":0,"k":0,"ix":4},"sa":{"a":0,"k":0,"ix":5},"nm":"Transform"}],"nm":"Group 1","np":2,"cix":2,"bm":0,"ix":1,"mn":"ADBE Vector Group","hd":false},{"ty":"st","c":{"a":0,"k":[0.145098039216,0.713725490196,0.521568627451,1],"ix":3},"o":{"a":0,"k":30,"ix":4},"w":{"a":0,"k":1,"ix":5},"lc":1,"lj":1,"ml":4,"bm":0,"nm":"Stroke 1","mn":"ADBE Vector Graphic - Stroke","hd":false}],"ip":0,"op":455.00001853253,"st":0,"bm":0},{"ddd":0,"ind":2,"ty":4,"nm":"Dot 01","sr":1,"ks":{"o":{"a":1,"k":[{"i":{"x":[0.667],"y":[1]},"o":{"x":[0.333],"y":[0]},"t":78,"s":[0]},{"i":{"x":[0.833],"y":[1]},"o":{"x":[0.333],"y":[0]},"t":127,"s":[0]},{"i":{"x":[0.833],"y":[1]},"o":{"x":[0.167],"y":[0]},"t":131,"s":[100]},{"i":{"x":[0.833],"y":[1]},"o":{"x":[0.167],"y":[0]},"t":168,"s":[100]},{"i":{"x":[0.833],"y":[1]},"o":{"x":[0.167],"y":[0]},"t":194,"s":[100]},{"i":{"x":[0.667],"y":[1]},"o":{"x":[0.167],"y":[0]},"t":227,"s":[0]},{"i":{"x":[0.667],"y":[1]},"o":{"x":[0.333],"y":[0]},"t":289,"s":[0]},{"i":{"x":[0.833],"y":[1]},"o":{"x":[0.333],"y":[0]},"t":338,"s":[0]},{"i":{"x":[0.833],"y":[1]},"o":{"x":[0.167],"y":[0]},"t":342,"s":[100]},{"i":{"x":[0.833],"y":[1]},"o":{"x":[0.167],"y":[0]},"t":379,"s":[100]},{"i":{"x":[0.833],"y":[1]},"o":{"x":[0.167],"y":[0]},"t":405,"s":[100]},{"t":438.000017840106,"s":[0]}],"ix":11},"r":{"a":0,"k":0,"ix":10},"p":{"a":1,"k":[{"i":{"x":0.667,"y":1},"o":{"x":0.333,"y":0},"t":98,"s":[764.134,780.998,0],"to":[11.025,-15.765,0],"ti":[0.491,19.106,0]},{"i":{"x":0.667,"y":1},"o":{"x":0.333,"y":0},"t":120.353,"s":[779.527,727.066,0],"to":[-0.254,-14.22,0],"ti":[-3.193,14.032,0]},{"i":{"x":0.667,"y":1},"o":{"x":0.333,"y":0},"t":128.02,"s":[781.805,684.618,0],"to":[5.28,-25.439,0],"ti":[-18.743,18.002,0]},{"i":{"x":0.667,"y":1},"o":{"x":0.333,"y":0},"t":139.036,"s":[819.126,617.551,0],"to":[25.707,-24.824,0],"ti":[-34.907,-1.634,0]},{"i":{"x":0.667,"y":1},"o":{"x":0.333,"y":0},"t":151.178,"s":[914.18,581.296,0],"to":[8.534,0.166,0],"ti":[-8.594,1.041,0]},{"i":{"x":0.667,"y":1},"o":{"x":0.333,"y":0},"t":153.929,"s":[940.093,580.707,0],"to":[42.93,-4.606,0],"ti":[0.122,43.168,0]},{"i":{"x":0.667,"y":1},"o":{"x":0.333,"y":0},"t":166.439,"s":[1017.033,494.941,0],"to":[0.901,-56.302,0],"ti":[54.925,-12.35,0]},{"i":{"x":0.667,"y":1},"o":{"x":0.333,"y":0},"t":181.068,"s":[910.115,408.1,0],"to":[-39.94,8.25,0],"ti":[-0.736,-40.639,0]},{"i":{"x":0.667,"y":1},"o":{"x":0.333,"y":0},"t":191.854,"s":[841.636,494.708,0],"to":[-0.109,7.56,0],"ti":[0.09,-7.549,0]},{"i":{"x":0.667,"y":1},"o":{"x":0.333,"y":0},"t":193.904,"s":[841.868,517.34,0],"to":[-0.371,31.02,0],"ti":[21.143,-23.108,0]},{"i":{"x":0.667,"y":1},"o":{"x":0.333,"y":0},"t":202.418,"s":[807.816,601.543,0],"to":[-23.548,25.738,0],"ti":[34.552,-0.642,0]},{"i":{"x":0.667,"y":1},"o":{"x":0.333,"y":0},"t":212.285,"s":[716.272,643.763,0],"to":[-16.438,0.106,0],"ti":[15.925,-4.878,0]},{"i":{"x":0.667,"y":1},"o":{"x":0.333,"y":0},"t":217.249,"s":[666.92,647.118,0],"to":[-66.815,19.611,0],"ti":[-53.541,-44.809,0]},{"i":{"x":0.667,"y":1},"o":{"x":0.333,"y":0},"t":239.103,"s":[635.541,798.51,0],"to":[38.526,33.068,0],"ti":[-28.203,42.376,0]},{"i":{"x":0.667,"y":1},"o":{"x":0.333,"y":0},"t":274.739,"s":[764.023,781.161,0],"to":[0,0,0],"ti":[0,0,0]},{"i":{"x":0.833,"y":1},"o":{"x":0.167,"y":0},"t":276,"s":[764.134,780.998,0],"to":[11.025,-15.765,0],"ti":[0,0,0]},{"i":{"x":0.667,"y":1},"o":{"x":0.333,"y":0},"t":309,"s":[764.134,780.998,0],"to":[11.025,-15.765,0],"ti":[0.491,19.106,0]},{"i":{"x":0.667,"y":1},"o":{"x":0.333,"y":0},"t":331.353,"s":[779.527,727.066,0],"to":[-0.254,-14.22,0],"ti":[-3.193,14.032,0]},{"i":{"x":0.667,"y":1},"o":{"x":0.333,"y":0},"t":339.02,"s":[781.805,684.618,0],"to":[5.28,-25.439,0],"ti":[-18.743,18.002,0]},{"i":{"x":0.667,"y":1},"o":{"x":0.333,"y":0},"t":350.036,"s":[819.126,617.551,0],"to":[25.707,-24.824,0],"ti":[-34.907,-1.634,0]},{"i":{"x":0.667,"y":1},"o":{"x":0.333,"y":0},"t":362.178,"s":[914.18,581.296,0],"to":[8.534,0.166,0],"ti":[-8.594,1.041,0]},{"i":{"x":0.667,"y":1},"o":{"x":0.333,"y":0},"t":364.929,"s":[940.093,580.707,0],"to":[42.93,-4.606,0],"ti":[0.122,43.168,0]},{"i":{"x":0.667,"y":1},"o":{"x":0.333,"y":0},"t":377.439,"s":[1017.033,494.941,0],"to":[0.901,-56.302,0],"ti":[54.925,-12.35,0]},{"i":{"x":0.667,"y":1},"o":{"x":0.333,"y":0},"t":392.068,"s":[910.115,408.1,0],"to":[-39.94,8.25,0],"ti":[-0.736,-40.639,0]},{"i":{"x":0.667,"y":1},"o":{"x":0.333,"y":0},"t":402.854,"s":[841.636,494.708,0],"to":[-0.109,7.56,0],"ti":[0.09,-7.549,0]},{"i":{"x":0.667,"y":1},"o":{"x":0.333,"y":0},"t":404.904,"s":[841.868,517.34,0],"to":[-0.371,31.02,0],"ti":[21.143,-23.108,0]},{"i":{"x":0.667,"y":1},"o":{"x":0.333,"y":0},"t":413.418,"s":[807.816,601.543,0],"to":[-23.548,25.738,0],"ti":[34.552,-0.642,0]},{"i":{"x":0.667,"y":1},"o":{"x":0.333,"y":0},"t":423.285,"s":[716.272,643.763,0],"to":[-16.438,0.106,0],"ti":[15.925,-4.878,0]},{"i":{"x":0.667,"y":0.719},"o":{"x":0.333,"y":0},"t":428.25,"s":[666.92,647.118,0],"to":[-66.815,19.611,0],"ti":[-53.541,-44.809,0]},{"i":{"x":0.667,"y":1},"o":{"x":0.333,"y":0.53},"t":450.103,"s":[635.541,798.51,0],"to":[38.526,33.068,0],"ti":[-28.203,42.376,0]},{"i":{"x":0.667,"y":1},"o":{"x":0.333,"y":0},"t":481.96,"s":[764.023,781.161,0],"to":[0,0,0],"ti":[0,0,0]},{"t":483.000019672993,"s":[764.134,780.998,0]}],"ix":2},"a":{"a":0,"k":[315,82,0],"ix":1},"s":{"a":0,"k":[17,17,100],"ix":6}},"ao":0,"shapes":[{"ty":"gr","it":[{"ind":0,"ty":"sh","ix":1,"ks":{"a":0,"k":{"i":[[18.225,0],[0,-18.225],[-18.225,0],[0,18.225]],"o":[[-18.225,0],[0,18.225],[18.225,0],[0,-18.225]],"v":[[0,-33],[-33,0],[0,33],[33,0]],"c":true},"ix":2},"nm":"Path 1","mn":"ADBE Vector Shape - Group","hd":false},{"ty":"fl","c":{"a":0,"k":[0.145097994337,0.713725968903,0.521568986481,1],"ix":4},"o":{"a":0,"k":100,"ix":5},"r":1,"bm":0,"nm":"Fill 1","mn":"ADBE Vector Graphic - Fill","hd":false},{"ty":"tr","p":{"a":0,"k":[315,82],"ix":2},"a":{"a":0,"k":[0,0],"ix":1},"s":{"a":0,"k":[100,100],"ix":3},"r":{"a":0,"k":0,"ix":6},"o":{"a":0,"k":100,"ix":7},"sk":{"a":0,"k":0,"ix":4},"sa":{"a":0,"k":0,"ix":5},"nm":"Transform"}],"nm":"Ellipse 1","np":3,"cix":2,"bm":0,"ix":1,"mn":"ADBE Vector Group","hd":false}],"ip":0,"op":455.00001853253,"st":0,"bm":0},{"ddd":0,"ind":3,"ty":4,"nm":"05","sr":1,"ks":{"o":{"a":0,"k":50,"ix":11},"r":{"a":0,"k":0,"ix":10},"p":{"a":0,"k":[566.511,378.475,0],"ix":2},"a":{"a":0,"k":[219.764,219.635,0],"ix":1},"s":{"a":0,"k":[100,100,100],"ix":6}},"ao":0,"shapes":[{"ty":"gr","it":[{"ind":0,"ty":"sh","ix":1,"ks":{"a":0,"k":{"i":[[0,0],[-1.075,-22.044],[2.582,-11.662],[18.851,-17.986],[34.802,1.667],[8.644,-1.087],[7.292,-3.223],[-42.034,-43.518],[-25.841,55.646],[0.799,17.832],[-4.105,13.594],[-55.818,-1.265],[-14.759,4.458],[-6.836,29.994],[41.232,15.012],[21.678,-32.877]],"o":[[-12.919,18.478],[0.403,11.8],[-5.329,25.497],[-25.706,24.654],[-8.612,-0.167],[-8.29,1.024],[-55.645,23.031],[41.849,44.656],[8.192,-16.214],[-0.536,-14],[15.11,-53.546],[15.207,0.241],[29.43,-8.565],[10.567,-42.558],[-36.636,-14.075],[0,0]],"v":[[51.285,-172.747],[36.032,-111.452],[33.614,-76.219],[-3.954,-9.072],[-98.811,26.88],[-124.937,27.501],[-148.44,33.761],[-177.48,174.729],[-34.614,152.026],[-26.381,99.399],[-21.372,57.753],[103.098,-35.614],[148.639,-38.983],[208.947,-102.342],[154.159,-205.311],[51.396,-172.91]],"c":true},"ix":2},"nm":"Path 1","mn":"ADBE Vector Shape - Group","hd":false},{"ty":"fl","c":{"a":0,"k":[0.145097994337,0.713725968903,0.521568986481,1],"ix":4},"o":{"a":1,"k":[{"i":{"x":[0.667],"y":[1]},"o":{"x":[0.333],"y":[0]},"t":66,"s":[0]},{"i":{"x":[0.833],"y":[1]},"o":{"x":[0.167],"y":[0]},"t":188,"s":[5]},{"t":305.000012422905,"s":[0]}],"ix":5},"r":1,"bm":0,"nm":"Fill 1","mn":"ADBE Vector Graphic - Fill","hd":false},{"ty":"tr","p":{"a":0,"k":[219.764,219.636],"ix":2},"a":{"a":0,"k":[0,0],"ix":1},"s":{"a":0,"k":[100,100],"ix":3},"r":{"a":0,"k":0,"ix":6},"o":{"a":0,"k":100,"ix":7},"sk":{"a":0,"k":0,"ix":4},"sa":{"a":0,"k":0,"ix":5},"nm":"Transform"}],"nm":"Group 1","np":2,"cix":2,"bm":0,"ix":1,"mn":"ADBE Vector Group","hd":false},{"ty":"st","c":{"a":0,"k":[0.145098039216,0.713725490196,0.521568627451,1],"ix":3},"o":{"a":0,"k":50,"ix":4},"w":{"a":0,"k":1,"ix":5},"lc":1,"lj":1,"ml":4,"bm":0,"nm":"Stroke 1","mn":"ADBE Vector Graphic - Stroke","hd":false}],"ip":0,"op":455.00001853253,"st":0,"bm":0},{"ddd":0,"ind":4,"ty":4,"nm":"Dot 05","sr":1,"ks":{"o":{"a":1,"k":[{"i":{"x":[0.833],"y":[1]},"o":{"x":[0.333],"y":[0]},"t":104,"s":[0]},{"i":{"x":[0.833],"y":[1]},"o":{"x":[0.167],"y":[0]},"t":108,"s":[100]},{"i":{"x":[0.833],"y":[1]},"o":{"x":[0.167],"y":[0]},"t":145,"s":[100]},{"i":{"x":[0.833],"y":[1]},"o":{"x":[0.167],"y":[0]},"t":171,"s":[100]},{"i":{"x":[0.833],"y":[1]},"o":{"x":[0.167],"y":[0]},"t":204,"s":[0]},{"i":{"x":[0.833],"y":[1]},"o":{"x":[0.333],"y":[0]},"t":304.425,"s":[0]},{"i":{"x":[0.833],"y":[1]},"o":{"x":[0.167],"y":[0]},"t":308.425,"s":[100]},{"i":{"x":[0.833],"y":[1]},"o":{"x":[0.167],"y":[0]},"t":345.425,"s":[100]},{"i":{"x":[0.833],"y":[1]},"o":{"x":[0.167],"y":[0]},"t":371.425,"s":[100]},{"t":404.425016472568,"s":[0]}],"ix":11},"r":{"a":0,"k":0,"ix":10},"p":{"a":1,"k":[{"i":{"x":0.667,"y":1},"o":{"x":0.333,"y":0},"t":68.575,"s":[617.549,205.889,0],"to":[-12.919,18.478,0],"ti":[-1.075,-22.044,0]},{"i":{"x":0.667,"y":1},"o":{"x":0.333,"y":0},"t":92.451,"s":[602.296,267.183,0],"to":[0.403,11.8,0],"ti":[2.582,-11.662,0]},{"i":{"x":0.667,"y":1},"o":{"x":0.333,"y":0},"t":98.689,"s":[599.878,302.416,0],"to":[-5.329,25.497,0],"ti":[18.851,-17.986,0]},{"i":{"x":0.667,"y":1},"o":{"x":0.333,"y":0},"t":109.751,"s":[562.31,369.563,0],"to":[-25.706,24.654,0],"ti":[34.802,1.667,0]},{"i":{"x":0.667,"y":1},"o":{"x":0.333,"y":0},"t":121.881,"s":[467.453,405.516,0],"to":[-8.612,-0.167,0],"ti":[8.644,-1.087,0]},{"i":{"x":0.667,"y":1},"o":{"x":0.333,"y":0},"t":124.663,"s":[441.327,406.137,0],"to":[-8.29,1.024,0],"ti":[7.292,-3.223,0]},{"i":{"x":0.667,"y":1},"o":{"x":0.333,"y":0},"t":127.191,"s":[417.824,412.397,0],"to":[-55.645,23.031,0],"ti":[-42.034,-43.518,0]},{"i":{"x":0.667,"y":1},"o":{"x":0.333,"y":0},"t":143.535,"s":[388.784,553.365,0],"to":[41.849,44.656,0],"ti":[-25.841,55.646,0]},{"i":{"x":0.667,"y":1},"o":{"x":0.333,"y":0},"t":159.045,"s":[531.65,530.662,0],"to":[8.192,-16.214,0],"ti":[0.799,17.832,0]},{"i":{"x":0.667,"y":1},"o":{"x":0.333,"y":0},"t":163.924,"s":[539.883,478.035,0],"to":[-0.536,-14,0],"ti":[-4.105,13.594,0]},{"i":{"x":0.667,"y":1},"o":{"x":0.333,"y":0},"t":167.765,"s":[544.892,436.389,0],"to":[15.11,-53.546,0],"ti":[-55.818,-1.265,0]},{"i":{"x":0.667,"y":1},"o":{"x":0.333,"y":0},"t":183.513,"s":[669.362,343.021,0],"to":[15.207,0.241,0],"ti":[-14.759,4.458,0]},{"i":{"x":0.667,"y":1},"o":{"x":0.333,"y":0},"t":188.114,"s":[714.903,339.652,0],"to":[29.43,-8.565,0],"ti":[-6.836,29.994,0]},{"i":{"x":0.667,"y":1},"o":{"x":0.333,"y":0},"t":197.936,"s":[775.211,276.293,0],"to":[10.567,-42.558,0],"ti":[41.232,15.012,0]},{"i":{"x":0.667,"y":1},"o":{"x":0.333,"y":0},"t":214.314,"s":[720.423,173.325,0],"to":[-36.636,-14.075,0],"ti":[21.678,-32.877,0]},{"i":{"x":0.667,"y":1},"o":{"x":0.333,"y":0},"t":245.736,"s":[617.66,205.726,0],"to":[0,0,0],"ti":[0,0,0]},{"i":{"x":0.833,"y":1},"o":{"x":0.167,"y":0},"t":247,"s":[617.549,205.889,0],"to":[-12.919,18.478,0],"ti":[0,0,0]},{"i":{"x":0.667,"y":1},"o":{"x":0.333,"y":0},"t":269,"s":[617.549,205.889,0],"to":[-12.919,18.478,0],"ti":[-1.075,-22.044,0]},{"i":{"x":0.667,"y":1},"o":{"x":0.333,"y":0},"t":292.876,"s":[602.296,267.183,0],"to":[0.403,11.8,0],"ti":[2.582,-11.662,0]},{"i":{"x":0.667,"y":1},"o":{"x":0.333,"y":0},"t":299.114,"s":[599.878,302.416,0],"to":[-5.329,25.497,0],"ti":[18.851,-17.986,0]},{"i":{"x":0.667,"y":1},"o":{"x":0.333,"y":0},"t":310.176,"s":[562.31,369.563,0],"to":[-25.706,24.654,0],"ti":[34.802,1.667,0]},{"i":{"x":0.667,"y":1},"o":{"x":0.333,"y":0},"t":322.306,"s":[467.453,405.516,0],"to":[-8.612,-0.167,0],"ti":[8.644,-1.087,0]},{"i":{"x":0.667,"y":1},"o":{"x":0.333,"y":0},"t":325.088,"s":[441.327,406.137,0],"to":[-8.29,1.024,0],"ti":[7.292,-3.223,0]},{"i":{"x":0.667,"y":1},"o":{"x":0.333,"y":0},"t":327.616,"s":[417.824,412.397,0],"to":[-55.645,23.031,0],"ti":[-42.034,-43.518,0]},{"i":{"x":0.667,"y":1},"o":{"x":0.333,"y":0},"t":343.96,"s":[388.784,553.365,0],"to":[41.849,44.656,0],"ti":[-25.841,55.646,0]},{"i":{"x":0.667,"y":1},"o":{"x":0.333,"y":0},"t":359.47,"s":[531.65,530.662,0],"to":[8.192,-16.214,0],"ti":[0.799,17.832,0]},{"i":{"x":0.667,"y":1},"o":{"x":0.333,"y":0},"t":364.349,"s":[539.883,478.035,0],"to":[-0.536,-14,0],"ti":[-4.105,13.594,0]},{"i":{"x":0.667,"y":1},"o":{"x":0.333,"y":0},"t":368.19,"s":[544.892,436.389,0],"to":[15.11,-53.546,0],"ti":[-55.818,-1.265,0]},{"i":{"x":0.667,"y":1},"o":{"x":0.333,"y":0},"t":383.938,"s":[669.362,343.021,0],"to":[15.207,0.241,0],"ti":[-14.759,4.458,0]},{"i":{"x":0.667,"y":1},"o":{"x":0.333,"y":0},"t":388.539,"s":[714.903,339.652,0],"to":[29.43,-8.565,0],"ti":[-6.836,29.994,0]},{"i":{"x":0.667,"y":1},"o":{"x":0.333,"y":0},"t":398.361,"s":[775.211,276.293,0],"to":[10.567,-42.558,0],"ti":[41.232,15.012,0]},{"i":{"x":0.667,"y":1},"o":{"x":0.333,"y":0},"t":414.739,"s":[720.423,173.325,0],"to":[-36.636,-14.075,0],"ti":[21.678,-32.877,0]},{"i":{"x":0.667,"y":1},"o":{"x":0.333,"y":0},"t":446.161,"s":[617.66,205.726,0],"to":[0,0,0],"ti":[0,0,0]},{"t":447.425018223994,"s":[617.549,205.889,0]}],"ix":2},"a":{"a":0,"k":[315,82,0],"ix":1},"s":{"a":0,"k":[17,17,100],"ix":6}},"ao":0,"shapes":[{"ty":"gr","it":[{"ind":0,"ty":"sh","ix":1,"ks":{"a":0,"k":{"i":[[18.225,0],[0,-18.225],[-18.225,0],[0,18.225]],"o":[[-18.225,0],[0,18.225],[18.225,0],[0,-18.225]],"v":[[0,-33],[-33,0],[0,33],[33,0]],"c":true},"ix":2},"nm":"Path 1","mn":"ADBE Vector Shape - Group","hd":false},{"ty":"fl","c":{"a":0,"k":[0.145097994337,0.713725968903,0.521568986481,1],"ix":4},"o":{"a":0,"k":100,"ix":5},"r":1,"bm":0,"nm":"Fill 1","mn":"ADBE Vector Graphic - Fill","hd":false},{"ty":"tr","p":{"a":0,"k":[315,82],"ix":2},"a":{"a":0,"k":[0,0],"ix":1},"s":{"a":0,"k":[100,100],"ix":3},"r":{"a":0,"k":0,"ix":6},"o":{"a":0,"k":100,"ix":7},"sk":{"a":0,"k":0,"ix":4},"sa":{"a":0,"k":0,"ix":5},"nm":"Transform"}],"nm":"Ellipse 1","np":3,"cix":2,"bm":0,"ix":1,"mn":"ADBE Vector Group","hd":false}],"ip":0,"op":455.00001853253,"st":0,"bm":0},{"ddd":0,"ind":5,"ty":4,"nm":"06","sr":1,"ks":{"o":{"a":0,"k":100,"ix":11},"r":{"a":0,"k":0,"ix":10},"p":{"a":0,"k":[806.881,1091.593,0],"ix":2},"a":{"a":0,"k":[221.927,221.049,0],"ix":1},"s":{"a":0,"k":[100,100,100],"ix":6}},"ao":0,"shapes":[{"ty":"gr","it":[{"ind":0,"ty":"sh","ix":1,"ks":{"a":0,"k":{"i":[[0,0],[-0.393,-18.856],[2.076,-12.226],[20.285,-19.457],[34.906,1.663],[8.594,-1.061],[7.305,-3.21],[-42.239,-43.545],[-25.599,55.875],[0.779,17.708],[-4.118,13.59],[-54.434,0.574],[-15.985,4.92],[-11.07,18.687],[40.966,24.567],[25.208,-37.936]],"o":[[-10.899,15.562],[0.095,12.277],[-4.313,27.785],[-25.695,24.787],[-8.561,-0.167],[-8.25,1.009],[-55.824,23.001],[41.98,44.557],[8.076,-16.153],[-0.56,-14.004],[14.786,-52.193],[16.498,-0.114],[20.765,-6.195],[24.749,-40.804],[-38.517,-24.137],[0,0]],"v":[[49.342,-171.562],[33.872,-118.087],[32.747,-81.282],[-5.757,-7.989],[-100.798,28.255],[-126.788,28.838],[-150.303,35.063],[-179.438,176.242],[-36.52,153.041],[-28.403,100.749],[-23.436,59.11],[97.089,-34.231],[146.606,-37.623],[196.928,-76.54],[167.163,-196.662],[49.452,-171.723]],"c":true},"ix":2},"nm":"Path 1","mn":"ADBE Vector Shape - Group","hd":false},{"ty":"fl","c":{"a":0,"k":[0.145097994337,0.713725968903,0.521568986481,1],"ix":4},"o":{"a":1,"k":[{"i":{"x":[0.667],"y":[1]},"o":{"x":[0.333],"y":[0]},"t":113,"s":[0]},{"i":{"x":[0.667],"y":[1]},"o":{"x":[0.333],"y":[0]},"t":233,"s":[3]},{"t":350.000014255792,"s":[0]}],"ix":5,"x":"var $bm_rt;\n$bm_rt = loopOut();"},"r":1,"bm":0,"nm":"Fill 1","mn":"ADBE Vector Graphic - Fill","hd":false},{"ty":"tr","p":{"a":0,"k":[221.926,221.05],"ix":2},"a":{"a":0,"k":[0,0],"ix":1},"s":{"a":0,"k":[100,100],"ix":3},"r":{"a":0,"k":0,"ix":6},"o":{"a":0,"k":100,"ix":7},"sk":{"a":0,"k":0,"ix":4},"sa":{"a":0,"k":0,"ix":5},"nm":"Transform"}],"nm":"Group 1","np":2,"cix":2,"bm":0,"ix":1,"mn":"ADBE Vector Group","hd":false},{"ty":"st","c":{"a":0,"k":[0.145098039216,0.713725490196,0.521568627451,1],"ix":3},"o":{"a":0,"k":30,"ix":4},"w":{"a":0,"k":1,"ix":5},"lc":1,"lj":1,"ml":4,"bm":0,"nm":"Stroke 1","mn":"ADBE Vector Graphic - Stroke","hd":false}],"ip":0,"op":455.00001853253,"st":0,"bm":0},{"ddd":0,"ind":6,"ty":4,"nm":"Dot 06","sr":1,"ks":{"o":{"a":1,"k":[{"i":{"x":[0.833],"y":[1]},"o":{"x":[0.333],"y":[0]},"t":34,"s":[0]},{"i":{"x":[0.833],"y":[1]},"o":{"x":[0.167],"y":[0]},"t":38,"s":[100]},{"i":{"x":[0.833],"y":[1]},"o":{"x":[0.167],"y":[0]},"t":75,"s":[100]},{"i":{"x":[0.833],"y":[1]},"o":{"x":[0.167],"y":[0]},"t":101,"s":[100]},{"i":{"x":[0.833],"y":[1]},"o":{"x":[0.167],"y":[0]},"t":134,"s":[0]},{"i":{"x":[0.833],"y":[1]},"o":{"x":[0.333],"y":[0]},"t":308.229,"s":[0]},{"i":{"x":[0.833],"y":[1]},"o":{"x":[0.167],"y":[0]},"t":312.229,"s":[100]},{"i":{"x":[0.833],"y":[1]},"o":{"x":[0.167],"y":[0]},"t":349.229,"s":[100]},{"i":{"x":[0.833],"y":[1]},"o":{"x":[0.167],"y":[0]},"t":375.229,"s":[100]},{"t":408.228766627498,"s":[0]}],"ix":11},"r":{"a":0,"k":0,"ix":10},"p":{"a":1,"k":[{"i":{"x":0.667,"y":1},"o":{"x":0.333,"y":0},"t":16,"s":[856.268,919.988,0],"to":[-10.899,15.562,0],"ti":[-0.393,-18.856,0]},{"i":{"x":0.667,"y":1},"o":{"x":0.333,"y":0},"t":38.385,"s":[840.799,973.463,0],"to":[0.095,12.277,0],"ti":[2.076,-12.226,0]},{"i":{"x":0.667,"y":1},"o":{"x":0.333,"y":0},"t":45.174,"s":[839.674,1010.268,0],"to":[-4.313,27.785,0],"ti":[20.285,-19.457,0]},{"i":{"x":0.667,"y":1},"o":{"x":0.333,"y":0},"t":57.286,"s":[801.17,1083.56,0],"to":[-25.695,24.787,0],"ti":[34.906,1.663,0]},{"i":{"x":0.667,"y":1},"o":{"x":0.333,"y":0},"t":69.49,"s":[706.129,1119.804,0],"to":[-8.561,-0.167,0],"ti":[8.594,-1.061,0]},{"i":{"x":0.667,"y":1},"o":{"x":0.333,"y":0},"t":72.265,"s":[680.139,1120.387,0],"to":[-8.25,1.009,0],"ti":[7.305,-3.21,0]},{"i":{"x":0.667,"y":1},"o":{"x":0.333,"y":0},"t":74.803,"s":[656.624,1126.613,0],"to":[-55.824,23.001,0],"ti":[-42.239,-43.545,0]},{"i":{"x":0.667,"y":1},"o":{"x":0.333,"y":0},"t":91.233,"s":[627.489,1267.792,0],"to":[41.98,44.557,0],"ti":[-25.599,55.875,0]},{"i":{"x":0.667,"y":1},"o":{"x":0.333,"y":0},"t":106.811,"s":[770.407,1244.591,0],"to":[8.076,-16.153,0],"ti":[0.779,17.708,0]},{"i":{"x":0.667,"y":1},"o":{"x":0.333,"y":0},"t":111.673,"s":[778.524,1192.299,0],"to":[-0.56,-14.004,0],"ti":[-4.118,13.59,0]},{"i":{"x":0.667,"y":1},"o":{"x":0.333,"y":0},"t":115.525,"s":[783.491,1150.66,0],"to":[14.786,-52.193,0],"ti":[-54.434,0.574,0]},{"i":{"x":0.667,"y":1},"o":{"x":0.333,"y":0},"t":130.933,"s":[904.016,1057.319,0],"to":[16.498,-0.114,0],"ti":[-15.985,4.92,0]},{"i":{"x":0.667,"y":1},"o":{"x":0.333,"y":0},"t":135.941,"s":[953.533,1053.926,0],"to":[20.765,-6.195,0],"ti":[-11.07,18.687,0]},{"i":{"x":0.667,"y":1},"o":{"x":0.333,"y":0},"t":142.835,"s":[1003.854,1015.01,0],"to":[24.749,-40.804,0],"ti":[40.966,24.567,0]},{"i":{"x":0.667,"y":1},"o":{"x":0.333,"y":0},"t":159.771,"s":[974.09,894.887,0],"to":[-38.517,-24.137,0],"ti":[25.208,-37.936,0]},{"i":{"x":0.667,"y":1},"o":{"x":0.333,"y":0},"t":193.735,"s":[856.379,919.826,0],"to":[0,0,0],"ti":[0,0,0]},{"i":{"x":0.833,"y":1},"o":{"x":0.167,"y":0},"t":195,"s":[856.268,919.988,0],"to":[-10.899,15.562,0],"ti":[0,0,0]},{"i":{"x":0.667,"y":1},"o":{"x":0.333,"y":0},"t":290.229,"s":[856.268,919.988,0],"to":[-10.899,15.562,0],"ti":[-0.393,-18.856,0]},{"i":{"x":0.667,"y":1},"o":{"x":0.333,"y":0},"t":312.614,"s":[840.799,973.463,0],"to":[0.095,12.277,0],"ti":[2.076,-12.226,0]},{"i":{"x":0.667,"y":1},"o":{"x":0.333,"y":0},"t":319.403,"s":[839.674,1010.268,0],"to":[-4.313,27.785,0],"ti":[20.285,-19.457,0]},{"i":{"x":0.667,"y":1},"o":{"x":0.333,"y":0},"t":331.515,"s":[801.17,1083.56,0],"to":[-25.695,24.787,0],"ti":[34.906,1.663,0]},{"i":{"x":0.667,"y":1},"o":{"x":0.333,"y":0},"t":343.719,"s":[706.129,1119.804,0],"to":[-8.561,-0.167,0],"ti":[8.594,-1.061,0]},{"i":{"x":0.667,"y":1},"o":{"x":0.333,"y":0},"t":346.494,"s":[680.139,1120.387,0],"to":[-8.25,1.009,0],"ti":[7.305,-3.21,0]},{"i":{"x":0.667,"y":1},"o":{"x":0.333,"y":0},"t":349.031,"s":[656.624,1126.613,0],"to":[-55.824,23.001,0],"ti":[-42.239,-43.545,0]},{"i":{"x":0.667,"y":1},"o":{"x":0.333,"y":0},"t":365.463,"s":[627.489,1267.792,0],"to":[41.98,44.557,0],"ti":[-25.599,55.875,0]},{"i":{"x":0.667,"y":1},"o":{"x":0.333,"y":0},"t":381.04,"s":[770.407,1244.591,0],"to":[8.076,-16.153,0],"ti":[0.779,17.708,0]},{"i":{"x":0.667,"y":1},"o":{"x":0.333,"y":0},"t":385.901,"s":[778.524,1192.299,0],"to":[-0.56,-14.004,0],"ti":[-4.118,13.59,0]},{"i":{"x":0.667,"y":1},"o":{"x":0.333,"y":0},"t":389.754,"s":[783.491,1150.66,0],"to":[14.786,-52.193,0],"ti":[-54.434,0.574,0]},{"i":{"x":0.667,"y":1},"o":{"x":0.333,"y":0},"t":405.161,"s":[904.016,1057.319,0],"to":[16.498,-0.114,0],"ti":[-15.985,4.92,0]},{"i":{"x":0.667,"y":1},"o":{"x":0.333,"y":0},"t":410.171,"s":[953.533,1053.926,0],"to":[20.765,-6.195,0],"ti":[-11.07,18.687,0]},{"i":{"x":0.667,"y":0.713},"o":{"x":0.333,"y":0},"t":417.064,"s":[1003.854,1015.01,0],"to":[24.749,-40.804,0],"ti":[40.966,24.567,0]},{"i":{"x":0.667,"y":1},"o":{"x":0.333,"y":0.656},"t":434,"s":[974.09,894.887,0],"to":[-38.517,-24.137,0],"ti":[25.208,-37.936,0]},{"i":{"x":0.667,"y":1},"o":{"x":0.333,"y":0},"t":471.466,"s":[856.379,919.826,0],"to":[0,0,0],"ti":[0,0,0]},{"t":473.000019265685,"s":[856.268,919.988,0]}],"ix":2},"a":{"a":0,"k":[315,82,0],"ix":1},"s":{"a":0,"k":[17,17,100],"ix":6}},"ao":0,"shapes":[{"ty":"gr","it":[{"ind":0,"ty":"sh","ix":1,"ks":{"a":0,"k":{"i":[[18.225,0],[0,-18.225],[-18.225,0],[0,18.225]],"o":[[-18.225,0],[0,18.225],[18.225,0],[0,-18.225]],"v":[[0,-33],[-33,0],[0,33],[33,0]],"c":true},"ix":2},"nm":"Path 1","mn":"ADBE Vector Shape - Group","hd":false},{"ty":"fl","c":{"a":0,"k":[0.145097994337,0.713725968903,0.521568986481,1],"ix":4},"o":{"a":0,"k":100,"ix":5},"r":1,"bm":0,"nm":"Fill 1","mn":"ADBE Vector Graphic - Fill","hd":false},{"ty":"tr","p":{"a":0,"k":[315,82],"ix":2},"a":{"a":0,"k":[0,0],"ix":1},"s":{"a":0,"k":[100,100],"ix":3},"r":{"a":0,"k":0,"ix":6},"o":{"a":0,"k":100,"ix":7},"sk":{"a":0,"k":0,"ix":4},"sa":{"a":0,"k":0,"ix":5},"nm":"Transform"}],"nm":"Ellipse 1","np":3,"cix":2,"bm":0,"ix":1,"mn":"ADBE Vector Group","hd":false}],"ip":0,"op":455.00001853253,"st":0,"bm":0},{"ddd":0,"ind":7,"ty":4,"nm":"07","sr":1,"ks":{"o":{"a":0,"k":50,"ix":11},"r":{"a":0,"k":0,"ix":10},"p":{"a":0,"k":[806.881,377.13,0],"ix":2},"a":{"a":0,"k":[221.927,221.049,0],"ix":1},"s":{"a":0,"k":[100,100,100],"ix":6}},"ao":0,"shapes":[{"ty":"gr","it":[{"ind":0,"ty":"sh","ix":1,"ks":{"a":0,"k":{"i":[[0,0],[-0.393,-18.856],[2.076,-12.227],[20.285,-19.457],[34.906,1.665],[8.594,-1.061],[7.305,-3.209],[-42.239,-43.545],[-25.6,55.876],[0.779,17.709],[-4.118,13.59],[-54.434,0.574],[-15.985,4.92],[-11.07,18.688],[40.966,24.568],[25.208,-37.936]],"o":[[-10.898,15.562],[0.095,12.277],[-4.314,27.784],[-25.695,24.788],[-8.561,-0.166],[-8.25,1.008],[-55.823,23.001],[41.981,44.556],[8.076,-16.153],[-0.56,-14.004],[14.786,-52.193],[16.498,-0.115],[20.765,-6.195],[24.749,-40.803],[-38.517,-24.137],[0,0]],"v":[[49.342,-171.561],[33.872,-118.087],[32.747,-81.281],[-5.757,-7.99],[-100.798,28.254],[-126.788,28.838],[-150.303,35.063],[-179.438,176.243],[-36.52,153.042],[-28.403,100.749],[-23.436,59.111],[97.089,-34.23],[146.606,-37.623],[196.928,-76.54],[167.163,-196.662],[49.452,-171.723]],"c":true},"ix":2},"nm":"Path 1","mn":"ADBE Vector Shape - Group","hd":false},{"ty":"fl","c":{"a":0,"k":[0.145097994337,0.713725968903,0.521568986481,1],"ix":4},"o":{"a":1,"k":[{"i":{"x":[0.833],"y":[1]},"o":{"x":[0.333],"y":[0]},"t":0,"s":[1]},{"i":{"x":[0.667],"y":[1]},"o":{"x":[0.167],"y":[0]},"t":83,"s":[0]},{"t":174.000007087165,"s":[1]}],"ix":5,"x":"var $bm_rt;\n$bm_rt = loopOut();"},"r":1,"bm":0,"nm":"Fill 1","mn":"ADBE Vector Graphic - Fill","hd":false},{"ty":"tr","p":{"a":0,"k":[221.926,221.049],"ix":2},"a":{"a":0,"k":[0,0],"ix":1},"s":{"a":0,"k":[100,100],"ix":3},"r":{"a":0,"k":0,"ix":6},"o":{"a":0,"k":100,"ix":7},"sk":{"a":0,"k":0,"ix":4},"sa":{"a":0,"k":0,"ix":5},"nm":"Transform"}],"nm":"Group 1","np":2,"cix":2,"bm":0,"ix":1,"mn":"ADBE Vector Group","hd":false},{"ty":"st","c":{"a":0,"k":[0.145098039216,0.713725490196,0.521568627451,1],"ix":3},"o":{"a":0,"k":30,"ix":4},"w":{"a":0,"k":1,"ix":5},"lc":1,"lj":1,"ml":4,"bm":0,"nm":"Stroke 1","mn":"ADBE Vector Graphic - Stroke","hd":false}],"ip":0,"op":455.00001853253,"st":0,"bm":0},{"ddd":0,"ind":8,"ty":4,"nm":"Dot 07","sr":1,"ks":{"o":{"a":1,"k":[{"i":{"x":[0.833],"y":[1]},"o":{"x":[0.333],"y":[0]},"t":53,"s":[0]},{"i":{"x":[0.833],"y":[1]},"o":{"x":[0.167],"y":[0]},"t":57,"s":[100]},{"i":{"x":[0.833],"y":[1]},"o":{"x":[0.167],"y":[0]},"t":94,"s":[100]},{"i":{"x":[0.833],"y":[1]},"o":{"x":[0.167],"y":[0]},"t":120,"s":[100]},{"i":{"x":[0.833],"y":[1]},"o":{"x":[0.167],"y":[0]},"t":153,"s":[0]},{"i":{"x":[0.833],"y":[1]},"o":{"x":[0.333],"y":[0]},"t":297,"s":[0]},{"i":{"x":[0.833],"y":[1]},"o":{"x":[0.167],"y":[0]},"t":301,"s":[100]},{"i":{"x":[0.833],"y":[1]},"o":{"x":[0.167],"y":[0]},"t":338,"s":[100]},{"i":{"x":[0.833],"y":[1]},"o":{"x":[0.167],"y":[0]},"t":364,"s":[100]},{"t":397.000016170141,"s":[0]}],"ix":11},"r":{"a":0,"k":0,"ix":10},"p":{"a":1,"k":[{"i":{"x":0.667,"y":1},"o":{"x":0.333,"y":0},"t":12,"s":[856.768,205.488,0],"to":[-10.898,15.562,0],"ti":[-0.393,-18.856,0]},{"i":{"x":0.667,"y":1},"o":{"x":0.333,"y":0},"t":41.501,"s":[841.299,258.962,0],"to":[0.095,12.277,0],"ti":[2.076,-12.227,0]},{"i":{"x":0.667,"y":1},"o":{"x":0.333,"y":0},"t":50.449,"s":[840.174,295.768,0],"to":[-4.314,27.784,0],"ti":[20.285,-19.457,0]},{"i":{"x":0.667,"y":1},"o":{"x":0.333,"y":0},"t":66.411,"s":[801.67,369.059,0],"to":[-25.695,24.788,0],"ti":[34.906,1.665,0]},{"i":{"x":0.667,"y":1},"o":{"x":0.333,"y":0},"t":82.495,"s":[706.629,405.303,0],"to":[-8.561,-0.166,0],"ti":[8.594,-1.061,0]},{"i":{"x":0.667,"y":1},"o":{"x":0.333,"y":0},"t":86.151,"s":[680.639,405.887,0],"to":[-8.25,1.008,0],"ti":[7.305,-3.209,0]},{"i":{"x":0.667,"y":1},"o":{"x":0.333,"y":0},"t":89.496,"s":[657.124,412.112,0],"to":[-55.823,23.001,0],"ti":[-42.239,-43.545,0]},{"i":{"x":0.667,"y":1},"o":{"x":0.333,"y":0},"t":111.149,"s":[627.989,553.292,0],"to":[41.981,44.556,0],"ti":[-25.6,55.876,0]},{"i":{"x":0.667,"y":1},"o":{"x":0.333,"y":0},"t":131.679,"s":[770.907,530.091,0],"to":[8.076,-16.153,0],"ti":[0.779,17.709,0]},{"i":{"x":0.667,"y":1},"o":{"x":0.333,"y":0},"t":138.085,"s":[779.024,477.798,0],"to":[-0.56,-14.004,0],"ti":[-4.118,13.59,0]},{"i":{"x":0.667,"y":1},"o":{"x":0.333,"y":0},"t":143.163,"s":[783.991,436.16,0],"to":[14.786,-52.193,0],"ti":[-54.434,0.574,0]},{"i":{"x":0.667,"y":1},"o":{"x":0.333,"y":0},"t":163.465,"s":[904.516,342.819,0],"to":[16.498,-0.115,0],"ti":[-15.985,4.92,0]},{"i":{"x":0.667,"y":1},"o":{"x":0.333,"y":0},"t":170.066,"s":[954.033,339.426,0],"to":[20.765,-6.195,0],"ti":[-11.07,18.688,0]},{"i":{"x":0.667,"y":1},"o":{"x":0.333,"y":0},"t":179.15,"s":[1004.354,300.509,0],"to":[24.749,-40.803,0],"ti":[40.966,24.568,0]},{"i":{"x":0.667,"y":0.966},"o":{"x":0.333,"y":0},"t":201.463,"s":[974.59,180.387,0],"to":[-38.517,-24.137,0],"ti":[25.208,-37.936,0]},{"i":{"x":0.667,"y":1},"o":{"x":0.333,"y":0.665},"t":245.728,"s":[856.879,205.326,0],"to":[0,0,0],"ti":[0,0,0]},{"i":{"x":0.833,"y":1},"o":{"x":0.167,"y":0},"t":247,"s":[856.768,205.488,0],"to":[-10.898,15.562,0],"ti":[0,0,0]},{"i":{"x":0.667,"y":1},"o":{"x":0.333,"y":0},"t":256,"s":[856.768,205.488,0],"to":[-10.898,15.562,0],"ti":[-0.393,-18.856,0]},{"i":{"x":0.667,"y":1},"o":{"x":0.333,"y":0},"t":278.51,"s":[841.299,258.962,0],"to":[0.095,12.277,0],"ti":[2.076,-12.227,0]},{"i":{"x":0.667,"y":1},"o":{"x":0.333,"y":0},"t":285.336,"s":[840.174,295.768,0],"to":[-4.314,27.784,0],"ti":[20.285,-19.457,0]},{"i":{"x":0.667,"y":1},"o":{"x":0.333,"y":0},"t":297.516,"s":[801.67,369.059,0],"to":[-25.695,24.788,0],"ti":[34.906,1.665,0]},{"i":{"x":0.667,"y":1},"o":{"x":0.333,"y":0},"t":309.789,"s":[706.629,405.303,0],"to":[-8.561,-0.166,0],"ti":[8.594,-1.061,0]},{"i":{"x":0.667,"y":1},"o":{"x":0.333,"y":0},"t":312.58,"s":[680.639,405.887,0],"to":[-8.25,1.008,0],"ti":[7.305,-3.209,0]},{"i":{"x":0.667,"y":1},"o":{"x":0.333,"y":0},"t":315.131,"s":[657.124,412.112,0],"to":[-55.823,23.001,0],"ti":[-42.239,-43.545,0]},{"i":{"x":0.667,"y":1},"o":{"x":0.333,"y":0},"t":331.654,"s":[627.989,553.292,0],"to":[41.981,44.556,0],"ti":[-25.6,55.876,0]},{"i":{"x":0.667,"y":1},"o":{"x":0.333,"y":0},"t":347.319,"s":[770.907,530.091,0],"to":[8.076,-16.153,0],"ti":[0.779,17.709,0]},{"i":{"x":0.667,"y":1},"o":{"x":0.333,"y":0},"t":352.208,"s":[779.024,477.798,0],"to":[-0.56,-14.004,0],"ti":[-4.118,13.59,0]},{"i":{"x":0.667,"y":1},"o":{"x":0.333,"y":0},"t":356.081,"s":[783.991,436.16,0],"to":[14.786,-52.193,0],"ti":[-54.434,0.574,0]},{"i":{"x":0.667,"y":1},"o":{"x":0.333,"y":0},"t":371.575,"s":[904.516,342.819,0],"to":[16.498,-0.115,0],"ti":[-15.985,4.92,0]},{"i":{"x":0.667,"y":1},"o":{"x":0.333,"y":0},"t":376.611,"s":[954.033,339.426,0],"to":[20.765,-6.195,0],"ti":[-11.07,18.688,0]},{"i":{"x":0.667,"y":1},"o":{"x":0.333,"y":0},"t":383.544,"s":[1004.354,300.509,0],"to":[24.749,-40.803,0],"ti":[40.966,24.568,0]},{"i":{"x":0.667,"y":1},"o":{"x":0.333,"y":0},"t":400.574,"s":[974.59,180.387,0],"to":[-38.517,-24.137,0],"ti":[25.208,-37.936,0]},{"i":{"x":0.667,"y":1},"o":{"x":0.333,"y":0},"t":434.728,"s":[856.879,205.326,0],"to":[0,0,0],"ti":[0,0,0]},{"t":436.000017758644,"s":[856.768,205.488,0]}],"ix":2},"a":{"a":0,"k":[315,82,0],"ix":1},"s":{"a":0,"k":[17,17,100],"ix":6}},"ao":0,"shapes":[{"ty":"gr","it":[{"ind":0,"ty":"sh","ix":1,"ks":{"a":0,"k":{"i":[[18.225,0],[0,-18.225],[-18.225,0],[0,18.225]],"o":[[-18.225,0],[0,18.225],[18.225,0],[0,-18.225]],"v":[[0,-33],[-33,0],[0,33],[33,0]],"c":true},"ix":2},"nm":"Path 1","mn":"ADBE Vector Shape - Group","hd":false},{"ty":"fl","c":{"a":0,"k":[0.145097994337,0.713725968903,0.521568986481,1],"ix":4},"o":{"a":0,"k":100,"ix":5},"r":1,"bm":0,"nm":"Fill 1","mn":"ADBE Vector Graphic - Fill","hd":false},{"ty":"tr","p":{"a":0,"k":[315,82],"ix":2},"a":{"a":0,"k":[0,0],"ix":1},"s":{"a":0,"k":[100,100],"ix":3},"r":{"a":0,"k":0,"ix":6},"o":{"a":0,"k":100,"ix":7},"sk":{"a":0,"k":0,"ix":4},"sa":{"a":0,"k":0,"ix":5},"nm":"Transform"}],"nm":"Ellipse 1","np":3,"cix":2,"bm":0,"ix":1,"mn":"ADBE Vector Group","hd":false}],"ip":0,"op":455.00001853253,"st":0,"bm":0},{"ddd":0,"ind":9,"ty":4,"nm":"04","sr":1,"ks":{"o":{"a":0,"k":50,"ix":11},"r":{"a":0,"k":0,"ix":10},"p":{"a":0,"k":[459.2,729.258,0],"ix":2},"a":{"a":0,"k":[103.272,97.229,0],"ix":1},"s":{"a":0,"k":[100,100,100],"ix":6}},"ao":0,"shapes":[{"ty":"gr","it":[{"ind":0,"ty":"sh","ix":1,"ks":{"a":0,"k":{"i":[[0,0],[33.616,-29.193],[-25.981,-36.48],[-37.25,14.489],[45.02,45.022]],"o":[[-30.902,-32.126],[-34.69,28.439],[22.476,33.14],[59.344,-22.496],[0,0]],"v":[[57.86,-62.454],[-61.166,-67.786],[-77.041,50.224],[26.894,82.49],[58.002,-62.31]],"c":true},"ix":2},"nm":"Path 1","mn":"ADBE Vector Shape - Group","hd":false},{"ty":"tr","p":{"a":0,"k":[103.272,97.229],"ix":2},"a":{"a":0,"k":[0,0],"ix":1},"s":{"a":0,"k":[100,100],"ix":3},"r":{"a":0,"k":0,"ix":6},"o":{"a":0,"k":100,"ix":7},"sk":{"a":0,"k":0,"ix":4},"sa":{"a":0,"k":0,"ix":5},"nm":"Transform"}],"nm":"Group 1","np":1,"cix":2,"bm":0,"ix":1,"mn":"ADBE Vector Group","hd":false},{"ty":"fl","c":{"a":0,"k":[0.145098045468,0.713725507259,0.521568655968,1],"ix":4},"o":{"a":1,"k":[{"i":{"x":[0.833],"y":[1]},"o":{"x":[0.333],"y":[0]},"t":33,"s":[0]},{"i":{"x":[0.833],"y":[1]},"o":{"x":[0.167],"y":[0]},"t":127,"s":[3]},{"t":226.000009205169,"s":[0]}],"ix":5},"r":1,"bm":0,"nm":"Fill 1","mn":"ADBE Vector Graphic - Fill","hd":false},{"ty":"st","c":{"a":0,"k":[0.145098039216,0.713725490196,0.521568627451,1],"ix":3},"o":{"a":0,"k":50,"ix":4},"w":{"a":0,"k":1,"ix":5},"lc":1,"lj":1,"ml":4,"bm":0,"nm":"Stroke 1","mn":"ADBE Vector Graphic - Stroke","hd":false}],"ip":0,"op":455.00001853253,"st":0,"bm":0},{"ddd":0,"ind":10,"ty":4,"nm":"Dot 04","sr":1,"ks":{"o":{"a":1,"k":[{"i":{"x":[0.833],"y":[1]},"o":{"x":[0.333],"y":[0]},"t":51,"s":[0]},{"i":{"x":[0.833],"y":[1]},"o":{"x":[0.333],"y":[0]},"t":135,"s":[0]},{"i":{"x":[0.833],"y":[1]},"o":{"x":[0.167],"y":[0]},"t":141,"s":[100]},{"i":{"x":[0.833],"y":[1]},"o":{"x":[0.167],"y":[0]},"t":178,"s":[100]},{"i":{"x":[0.833],"y":[1]},"o":{"x":[0.167],"y":[0]},"t":216,"s":[0]},{"i":{"x":[0.833],"y":[1]},"o":{"x":[0.333],"y":[0]},"t":277,"s":[0]},{"i":{"x":[0.833],"y":[1]},"o":{"x":[0.333],"y":[0]},"t":361,"s":[0]},{"i":{"x":[0.833],"y":[1]},"o":{"x":[0.167],"y":[0]},"t":367,"s":[100]},{"i":{"x":[0.833],"y":[1]},"o":{"x":[0.167],"y":[0]},"t":404,"s":[100]},{"t":442.000018003029,"s":[0]}],"ix":11},"r":{"a":0,"k":0,"ix":10},"p":{"a":1,"k":[{"i":{"x":0.667,"y":1},"o":{"x":0.333,"y":0},"t":133,"s":[516.632,666.9,0],"to":[-30.902,-32.126,0],"ti":[33.616,-29.193,0]},{"i":{"x":0.667,"y":1},"o":{"x":0.333,"y":0},"t":166.768,"s":[397.606,661.568,0],"to":[-34.69,28.439,0],"ti":[-25.981,-36.48,0]},{"i":{"x":0.667,"y":1},"o":{"x":0.333,"y":0},"t":184.466,"s":[381.731,779.578,0],"to":[22.476,33.14,0],"ti":[-37.25,14.489,0]},{"i":{"x":0.667,"y":1},"o":{"x":0.333,"y":0},"t":199.826,"s":[485.666,811.844,0],"to":[59.344,-22.496,0],"ti":[45.02,45.022,0]},{"i":{"x":0.667,"y":1},"o":{"x":0.333,"y":0},"t":238.814,"s":[516.775,667.044,0],"to":[0,0,0],"ti":[0,0,0]},{"i":{"x":0.833,"y":1},"o":{"x":0.167,"y":0},"t":240,"s":[516.632,666.9,0],"to":[-30.902,-32.126,0],"ti":[0,0,0]},{"i":{"x":0.667,"y":1},"o":{"x":0.333,"y":0},"t":359,"s":[516.632,666.9,0],"to":[-30.902,-32.126,0],"ti":[33.616,-29.193,0]},{"i":{"x":0.667,"y":1},"o":{"x":0.333,"y":0},"t":392.768,"s":[397.606,661.568,0],"to":[-34.69,28.439,0],"ti":[-25.981,-36.48,0]},{"i":{"x":0.667,"y":1},"o":{"x":0.333,"y":0},"t":410.466,"s":[381.731,779.578,0],"to":[22.476,33.14,0],"ti":[-37.25,14.489,0]},{"i":{"x":0.667,"y":1},"o":{"x":0.333,"y":0},"t":425.826,"s":[485.666,811.844,0],"to":[59.344,-22.496,0],"ti":[45.02,45.022,0]},{"i":{"x":0.667,"y":1},"o":{"x":0.333,"y":0},"t":464.814,"s":[516.775,667.044,0],"to":[0,0,0],"ti":[0,0,0]},{"t":466.000018980569,"s":[516.632,666.9,0]}],"ix":2},"a":{"a":0,"k":[315,82,0],"ix":1},"s":{"a":0,"k":[17,17,100],"ix":6}},"ao":0,"shapes":[{"ty":"gr","it":[{"ind":0,"ty":"sh","ix":1,"ks":{"a":0,"k":{"i":[[18.225,0],[0,-18.225],[-18.225,0],[0,18.225]],"o":[[-18.225,0],[0,18.225],[18.225,0],[0,-18.225]],"v":[[0,-33],[-33,0],[0,33],[33,0]],"c":true},"ix":2},"nm":"Path 1","mn":"ADBE Vector Shape - Group","hd":false},{"ty":"fl","c":{"a":0,"k":[0.145097994337,0.713725968903,0.521568986481,1],"ix":4},"o":{"a":0,"k":100,"ix":5},"r":1,"bm":0,"nm":"Fill 1","mn":"ADBE Vector Graphic - Fill","hd":false},{"ty":"tr","p":{"a":0,"k":[315,82],"ix":2},"a":{"a":0,"k":[0,0],"ix":1},"s":{"a":0,"k":[100,100],"ix":3},"r":{"a":0,"k":0,"ix":6},"o":{"a":0,"k":100,"ix":7},"sk":{"a":0,"k":0,"ix":4},"sa":{"a":0,"k":0,"ix":5},"nm":"Transform"}],"nm":"Ellipse 1","np":3,"cix":2,"bm":0,"ix":1,"mn":"ADBE Vector Group","hd":false}],"ip":0,"op":455.00001853253,"st":0,"bm":0},{"ddd":0,"ind":11,"ty":4,"nm":"02","sr":1,"ks":{"o":{"a":0,"k":30,"ix":11},"r":{"a":0,"k":0,"ix":10},"p":{"a":0,"k":[436.181,264.571,0],"ix":2},"a":{"a":0,"k":[103.658,102.155,0],"ix":1},"s":{"a":0,"k":[100,100,100],"ix":6}},"ao":0,"shapes":[{"ty":"gr","it":[{"ind":0,"ty":"sh","ix":1,"ks":{"a":0,"k":{"i":[[0,0],[50.864,-5.383],[-73.428,-44.13],[0.263,67.696]],"o":[[0.589,-51.19],[-85.374,8.931],[58.216,34.285],[0,0]],"v":[[102.819,-8.725],[6.282,-96.523],[-29.98,67.621],[102.819,-8.524]],"c":true},"ix":2},"nm":"Path 1","mn":"ADBE Vector Shape - Group","hd":false},{"ty":"fl","c":{"a":0,"k":[0.145097994337,0.713725968903,0.521568986481,1],"ix":4},"o":{"a":1,"k":[{"i":{"x":[0.833],"y":[1]},"o":{"x":[0.333],"y":[0]},"t":78,"s":[0]},{"i":{"x":[0.833],"y":[1]},"o":{"x":[0.167],"y":[0]},"t":204,"s":[2]},{"t":326.000013278252,"s":[0]}],"ix":5},"r":1,"bm":0,"nm":"Fill 1","mn":"ADBE Vector Graphic - Fill","hd":false},{"ty":"tr","p":{"a":0,"k":[103.658,102.156],"ix":2},"a":{"a":0,"k":[0,0],"ix":1},"s":{"a":0,"k":[100,100],"ix":3},"r":{"a":0,"k":0,"ix":6},"o":{"a":0,"k":100,"ix":7},"sk":{"a":0,"k":0,"ix":4},"sa":{"a":0,"k":0,"ix":5},"nm":"Transform"}],"nm":"Group 1","np":2,"cix":2,"bm":0,"ix":1,"mn":"ADBE Vector Group","hd":false},{"ty":"st","c":{"a":0,"k":[0.145098039216,0.713725490196,0.521568627451,1],"ix":3},"o":{"a":0,"k":50,"ix":4},"w":{"a":0,"k":1,"ix":5},"lc":1,"lj":1,"ml":4,"bm":0,"nm":"Stroke 1","mn":"ADBE Vector Graphic - Stroke","hd":false}],"ip":0,"op":455.00001853253,"st":0,"bm":0},{"ddd":0,"ind":12,"ty":4,"nm":"Dot 02","sr":1,"ks":{"o":{"a":1,"k":[{"i":{"x":[0.833],"y":[1]},"o":{"x":[0.333],"y":[0]},"t":3,"s":[0]},{"i":{"x":[0.833],"y":[1]},"o":{"x":[0.333],"y":[0]},"t":87,"s":[0]},{"i":{"x":[0.833],"y":[1]},"o":{"x":[0.167],"y":[0]},"t":93,"s":[100]},{"i":{"x":[0.833],"y":[1]},"o":{"x":[0.167],"y":[0]},"t":130,"s":[100]},{"i":{"x":[0.833],"y":[1]},"o":{"x":[0.167],"y":[0]},"t":161,"s":[0]},{"i":{"x":[0.833],"y":[1]},"o":{"x":[0.333],"y":[0]},"t":225,"s":[0]},{"i":{"x":[0.833],"y":[1]},"o":{"x":[0.333],"y":[0]},"t":309,"s":[0]},{"i":{"x":[0.833],"y":[1]},"o":{"x":[0.167],"y":[0]},"t":315,"s":[100]},{"i":{"x":[0.833],"y":[1]},"o":{"x":[0.167],"y":[0]},"t":352,"s":[100]},{"t":383.00001559991,"s":[0]}],"ix":11},"r":{"a":0,"k":0,"ix":10},"p":{"a":1,"k":[{"i":{"x":0.667,"y":1},"o":{"x":0.333,"y":0},"t":86.06,"s":[538.977,255.681,0],"to":[0.589,-51.19,0],"ti":[50.864,-5.383,0]},{"i":{"x":0.667,"y":1},"o":{"x":0.333,"y":0},"t":121.813,"s":[442.44,167.883,0],"to":[-85.374,8.931,0],"ti":[-73.428,-44.13,0]},{"i":{"x":0.667,"y":1},"o":{"x":0.333,"y":0},"t":150.931,"s":[406.178,332.026,0],"to":[58.216,34.285,0],"ti":[0.263,67.696,0]},{"i":{"x":0.667,"y":1},"o":{"x":0.333,"y":0},"t":190.834,"s":[538.977,255.881,0],"to":[0,0,0],"ti":[0,0,0]},{"i":{"x":0.833,"y":1},"o":{"x":0.167,"y":0},"t":192,"s":[538.977,255.681,0],"to":[0.589,-51.19,0],"ti":[0,0,0]},{"i":{"x":0.667,"y":1},"o":{"x":0.333,"y":0},"t":308.06,"s":[538.977,255.681,0],"to":[0.589,-51.19,0],"ti":[50.864,-5.383,0]},{"i":{"x":0.667,"y":1},"o":{"x":0.333,"y":0},"t":343.813,"s":[442.44,167.883,0],"to":[-85.374,8.931,0],"ti":[-73.428,-44.13,0]},{"i":{"x":0.667,"y":1},"o":{"x":0.333,"y":0},"t":372.931,"s":[406.178,332.026,0],"to":[58.216,34.285,0],"ti":[0.263,67.696,0]},{"i":{"x":0.667,"y":1},"o":{"x":0.333,"y":0},"t":412.834,"s":[538.977,255.881,0],"to":[0,0,0],"ti":[0,0,0]},{"t":414.000016862566,"s":[538.977,255.681,0]}],"ix":2},"a":{"a":0,"k":[315,82,0],"ix":1},"s":{"a":0,"k":[17,17,100],"ix":6}},"ao":0,"shapes":[{"ty":"gr","it":[{"ind":0,"ty":"sh","ix":1,"ks":{"a":0,"k":{"i":[[18.225,0],[0,-18.225],[-18.225,0],[0,18.225]],"o":[[-18.225,0],[0,18.225],[18.225,0],[0,-18.225]],"v":[[0,-33],[-33,0],[0,33],[33,0]],"c":true},"ix":2},"nm":"Path 1","mn":"ADBE Vector Shape - Group","hd":false},{"ty":"fl","c":{"a":0,"k":[0.145097994337,0.713725968903,0.521568986481,1],"ix":4},"o":{"a":0,"k":100,"ix":5},"r":1,"bm":0,"nm":"Fill 1","mn":"ADBE Vector Graphic - Fill","hd":false},{"ty":"tr","p":{"a":0,"k":[315,82],"ix":2},"a":{"a":0,"k":[0,0],"ix":1},"s":{"a":0,"k":[100,100],"ix":3},"r":{"a":0,"k":0,"ix":6},"o":{"a":0,"k":100,"ix":7},"sk":{"a":0,"k":0,"ix":4},"sa":{"a":0,"k":0,"ix":5},"nm":"Transform"}],"nm":"Ellipse 1","np":3,"cix":2,"bm":0,"ix":1,"mn":"ADBE Vector Group","hd":false}],"ip":0,"op":455.00001853253,"st":0,"bm":0},{"ddd":0,"ind":13,"ty":4,"nm":"03","sr":1,"ks":{"o":{"a":0,"k":30,"ix":11},"r":{"a":0,"k":0,"ix":10},"p":{"a":0,"k":[566.511,1092.936,0],"ix":2},"a":{"a":0,"k":[219.764,219.635,0],"ix":1},"s":{"a":0,"k":[100,100,100],"ix":6}},"ao":0,"shapes":[{"ty":"gr","it":[{"ind":0,"ty":"sh","ix":1,"ks":{"a":0,"k":{"i":[[0,0],[-1.075,-22.044],[2.582,-11.662],[18.851,-17.987],[34.802,1.665],[8.644,-1.086],[7.292,-3.223],[-42.034,-43.517],[-25.841,55.645],[0.799,17.831],[-4.105,13.593],[-55.818,-1.266],[-14.759,4.457],[-6.836,29.994],[41.232,15.014],[21.678,-32.877]],"o":[[-12.919,18.479],[0.403,11.8],[-5.329,25.497],[-25.706,24.654],[-8.612,-0.167],[-8.29,1.024],[-55.645,23.032],[41.848,44.655],[8.192,-16.215],[-0.536,-14],[15.11,-53.547],[15.207,0.24],[29.43,-8.564],[10.567,-42.559],[-36.636,-14.075],[0,0]],"v":[[51.285,-172.746],[36.032,-111.452],[33.614,-76.218],[-3.954,-9.07],[-98.811,26.882],[-124.937,27.502],[-148.44,33.762],[-177.48,174.73],[-34.614,152.028],[-26.381,99.401],[-21.372,57.755],[103.098,-35.613],[148.639,-38.983],[208.947,-102.34],[154.159,-205.31],[51.396,-172.909]],"c":true},"ix":2},"nm":"Path 1","mn":"ADBE Vector Shape - Group","hd":false},{"ty":"fl","c":{"a":0,"k":[0.145097994337,0.713725968903,0.521568986481,1],"ix":4},"o":{"a":1,"k":[{"i":{"x":[0.833],"y":[1]},"o":{"x":[0.333],"y":[0]},"t":106,"s":[0]},{"i":{"x":[0.833],"y":[1]},"o":{"x":[0.167],"y":[0]},"t":223,"s":[3]},{"t":353.000014377985,"s":[1]}],"ix":5},"r":1,"bm":0,"nm":"Fill 1","mn":"ADBE Vector Graphic - Fill","hd":false},{"ty":"tr","p":{"a":0,"k":[219.764,219.635],"ix":2},"a":{"a":0,"k":[0,0],"ix":1},"s":{"a":0,"k":[100,100],"ix":3},"r":{"a":0,"k":0,"ix":6},"o":{"a":0,"k":100,"ix":7},"sk":{"a":0,"k":0,"ix":4},"sa":{"a":0,"k":0,"ix":5},"nm":"Transform"}],"nm":"Group 1","np":2,"cix":2,"bm":0,"ix":1,"mn":"ADBE Vector Group","hd":false},{"ty":"st","c":{"a":0,"k":[0.145098039216,0.713725490196,0.521568627451,1],"ix":3},"o":{"a":0,"k":50,"ix":4},"w":{"a":0,"k":1,"ix":5},"lc":1,"lj":1,"ml":4,"bm":0,"nm":"Stroke 1","mn":"ADBE Vector Graphic - Stroke","hd":false}],"ip":0,"op":455.00001853253,"st":0,"bm":0},{"ddd":0,"ind":14,"ty":4,"nm":"Dot 03","sr":1,"ks":{"o":{"a":1,"k":[{"i":{"x":[0.833],"y":[1]},"o":{"x":[0.333],"y":[0]},"t":25,"s":[0]},{"i":{"x":[0.833],"y":[1]},"o":{"x":[0.333],"y":[0]},"t":65,"s":[0]},{"i":{"x":[0.833],"y":[1]},"o":{"x":[0.167],"y":[0]},"t":78,"s":[100]},{"i":{"x":[0.833],"y":[1]},"o":{"x":[0.167],"y":[0]},"t":115,"s":[100]},{"i":{"x":[0.81],"y":[1]},"o":{"x":[0.188],"y":[0]},"t":141,"s":[100]},{"i":{"x":[0.833],"y":[1]},"o":{"x":[0.167],"y":[0]},"t":170,"s":[0]},{"i":{"x":[0.833],"y":[1]},"o":{"x":[0.333],"y":[0]},"t":217,"s":[0]},{"i":{"x":[0.833],"y":[1]},"o":{"x":[0.333],"y":[0]},"t":244,"s":[0]},{"i":{"x":[0.833],"y":[1]},"o":{"x":[0.167],"y":[0]},"t":266,"s":[100]},{"i":{"x":[0.833],"y":[1]},"o":{"x":[0.167],"y":[0]},"t":307,"s":[0]},{"i":{"x":[0.81],"y":[1]},"o":{"x":[0.188],"y":[0]},"t":360,"s":[100]},{"t":379.000015436986,"s":[0]}],"ix":11},"r":{"a":0,"k":0,"ix":10},"p":{"a":1,"k":[{"i":{"x":0.667,"y":1},"o":{"x":0.333,"y":0},"t":13,"s":[617.549,920.389,0],"to":[-12.919,18.479,0],"ti":[-1.075,-22.044,0]},{"i":{"x":0.667,"y":1},"o":{"x":0.333,"y":0},"t":35.883,"s":[602.296,981.683,0],"to":[0.403,11.8,0],"ti":[2.582,-11.662,0]},{"i":{"x":0.667,"y":1},"o":{"x":0.333,"y":0},"t":41.861,"s":[599.878,1016.917,0],"to":[-5.329,25.497,0],"ti":[18.851,-17.987,0]},{"i":{"x":0.667,"y":1},"o":{"x":0.333,"y":0},"t":52.464,"s":[562.31,1084.065,0],"to":[-25.706,24.654,0],"ti":[34.802,1.665,0]},{"i":{"x":0.667,"y":1},"o":{"x":0.333,"y":0},"t":64.088,"s":[467.453,1120.017,0],"to":[-8.612,-0.167,0],"ti":[8.644,-1.086,0]},{"i":{"x":0.667,"y":1},"o":{"x":0.333,"y":0},"t":66.754,"s":[441.327,1120.637,0],"to":[-8.29,1.024,0],"ti":[7.292,-3.223,0]},{"i":{"x":0.667,"y":1},"o":{"x":0.333,"y":0},"t":69.178,"s":[417.824,1126.897,0],"to":[-55.645,23.032,0],"ti":[-42.034,-43.517,0]},{"i":{"x":0.667,"y":1},"o":{"x":0.333,"y":0},"t":84.84,"s":[388.784,1267.865,0],"to":[41.848,44.655,0],"ti":[-25.841,55.645,0]},{"i":{"x":0.667,"y":1},"o":{"x":0.333,"y":0},"t":99.705,"s":[531.65,1245.163,0],"to":[8.192,-16.215,0],"ti":[0.799,17.831,0]},{"i":{"x":0.667,"y":1},"o":{"x":0.333,"y":0},"t":104.381,"s":[539.883,1192.536,0],"to":[-0.536,-14,0],"ti":[-4.105,13.593,0]},{"i":{"x":0.667,"y":1},"o":{"x":0.333,"y":0},"t":108.063,"s":[544.892,1150.89,0],"to":[15.11,-53.547,0],"ti":[-55.818,-1.266,0]},{"i":{"x":0.667,"y":1},"o":{"x":0.333,"y":0},"t":123.154,"s":[669.362,1057.522,0],"to":[15.207,0.24,0],"ti":[-14.759,4.457,0]},{"i":{"x":0.667,"y":1},"o":{"x":0.333,"y":0},"t":127.564,"s":[714.903,1054.152,0],"to":[29.43,-8.564,0],"ti":[-6.836,29.994,0]},{"i":{"x":0.667,"y":1},"o":{"x":0.333,"y":0},"t":136.978,"s":[775.211,990.795,0],"to":[10.567,-42.559,0],"ti":[41.232,15.014,0]},{"i":{"x":0.667,"y":1},"o":{"x":0.333,"y":0},"t":152.675,"s":[720.423,887.825,0],"to":[-36.636,-14.075,0],"ti":[21.678,-32.877,0]},{"i":{"x":0.667,"y":1},"o":{"x":0.333,"y":0},"t":182.789,"s":[617.66,920.226,0],"to":[0,0,0],"ti":[0,0,0]},{"i":{"x":0.833,"y":1},"o":{"x":0.167,"y":0},"t":184,"s":[617.549,920.389,0],"to":[-12.919,18.479,0],"ti":[0,0,0]},{"i":{"x":0.667,"y":1},"o":{"x":0.333,"y":0},"t":276.211,"s":[617.549,920.389,0],"to":[-12.919,18.479,0],"ti":[-1.075,-22.044,0]},{"i":{"x":0.667,"y":1},"o":{"x":0.333,"y":0},"t":299.094,"s":[602.296,981.683,0],"to":[0.403,11.8,0],"ti":[2.582,-11.662,0]},{"i":{"x":0.667,"y":1},"o":{"x":0.333,"y":0},"t":305.073,"s":[599.878,1016.917,0],"to":[-5.329,25.497,0],"ti":[18.851,-17.987,0]},{"i":{"x":0.667,"y":1},"o":{"x":0.333,"y":0},"t":315.675,"s":[562.31,1084.065,0],"to":[-25.706,24.654,0],"ti":[34.802,1.665,0]},{"i":{"x":0.667,"y":1},"o":{"x":0.333,"y":0},"t":327.299,"s":[467.453,1120.017,0],"to":[-8.612,-0.167,0],"ti":[8.644,-1.086,0]},{"i":{"x":0.667,"y":1},"o":{"x":0.333,"y":0},"t":329.965,"s":[441.327,1120.637,0],"to":[-8.29,1.024,0],"ti":[7.292,-3.223,0]},{"i":{"x":0.667,"y":1},"o":{"x":0.333,"y":0},"t":332.389,"s":[417.824,1126.897,0],"to":[-55.645,23.032,0],"ti":[-42.034,-43.517,0]},{"i":{"x":0.667,"y":1},"o":{"x":0.333,"y":0},"t":348.051,"s":[388.784,1267.865,0],"to":[41.848,44.655,0],"ti":[-25.841,55.645,0]},{"i":{"x":0.667,"y":1},"o":{"x":0.333,"y":0},"t":362.916,"s":[531.65,1245.163,0],"to":[8.192,-16.215,0],"ti":[0.799,17.831,0]},{"i":{"x":0.667,"y":1},"o":{"x":0.333,"y":0},"t":367.593,"s":[539.883,1192.536,0],"to":[-0.536,-14,0],"ti":[-4.105,13.593,0]},{"i":{"x":0.667,"y":1},"o":{"x":0.333,"y":0},"t":371.274,"s":[544.892,1150.89,0],"to":[15.11,-53.547,0],"ti":[-55.818,-1.266,0]},{"i":{"x":0.667,"y":1},"o":{"x":0.333,"y":0},"t":386.365,"s":[669.362,1057.522,0],"to":[15.207,0.24,0],"ti":[-14.759,4.457,0]},{"i":{"x":0.667,"y":1},"o":{"x":0.333,"y":0},"t":390.775,"s":[714.903,1054.152,0],"to":[29.43,-8.564,0],"ti":[-6.836,29.994,0]},{"i":{"x":0.667,"y":1},"o":{"x":0.333,"y":0},"t":400.189,"s":[775.211,990.795,0],"to":[10.567,-42.559,0],"ti":[41.232,15.014,0]},{"i":{"x":0.667,"y":1},"o":{"x":0.333,"y":0},"t":415.886,"s":[720.423,887.825,0],"to":[-36.636,-14.075,0],"ti":[21.678,-32.877,0]},{"i":{"x":0.667,"y":1},"o":{"x":0.333,"y":0},"t":446,"s":[617.66,920.226,0],"to":[0,0,0],"ti":[0,0,0]},{"t":447.211268215288,"s":[617.549,920.389,0]}],"ix":2},"a":{"a":0,"k":[315,82,0],"ix":1},"s":{"a":0,"k":[17,17,100],"ix":6}},"ao":0,"shapes":[{"ty":"gr","it":[{"ind":0,"ty":"sh","ix":1,"ks":{"a":0,"k":{"i":[[18.225,0],[0,-18.225],[-18.225,0],[0,18.225]],"o":[[-18.225,0],[0,18.225],[18.225,0],[0,-18.225]],"v":[[0,-33],[-33,0],[0,33],[33,0]],"c":true},"ix":2},"nm":"Path 1","mn":"ADBE Vector Shape - Group","hd":false},{"ty":"fl","c":{"a":0,"k":[0.145097994337,0.713725968903,0.521568986481,1],"ix":4},"o":{"a":0,"k":100,"ix":5},"r":1,"bm":0,"nm":"Fill 1","mn":"ADBE Vector Graphic - Fill","hd":false},{"ty":"tr","p":{"a":0,"k":[315,82],"ix":2},"a":{"a":0,"k":[0,0],"ix":1},"s":{"a":0,"k":[100,100],"ix":3},"r":{"a":0,"k":0,"ix":6},"o":{"a":0,"k":100,"ix":7},"sk":{"a":0,"k":0,"ix":4},"sa":{"a":0,"k":0,"ix":5},"nm":"Transform"}],"nm":"Ellipse 1","np":3,"cix":2,"bm":0,"ix":1,"mn":"ADBE Vector Group","hd":false}],"ip":0,"op":455.00001853253,"st":0,"bm":0}]}],"layers":[{"ddd":0,"ind":1,"ty":0,"nm":"Pre-comp 1","refId":"comp_0","sr":1,"ks":{"o":{"a":0,"k":30,"ix":11},"r":{"a":0,"k":180,"ix":10},"p":{"a":0,"k":[-188,517,0],"ix":2},"a":{"a":0,"k":[960,713,0],"ix":1},"s":{"a":0,"k":[100,100,100],"ix":6}},"ao":0,"w":1920,"h":1426,"ip":0,"op":455.00001853253,"st":0,"bm":0},{"ddd":0,"ind":2,"ty":0,"nm":"Pre-comp 1","refId":"comp_0","sr":1,"ks":{"o":{"a":0,"k":100,"ix":11},"r":{"a":0,"k":0,"ix":10},"p":{"a":0,"k":[1780,713,0],"ix":2},"a":{"a":0,"k":[960,713,0],"ix":1},"s":{"a":0,"k":[100,100,100],"ix":6}},"ao":0,"w":1920,"h":1426,"ip":0,"op":455.00001853253,"st":0,"bm":0}],"markers":[]}